README
setup.py
scripts/wordpress2markdown
wordpress2markdown/WordpressToMarkdown.py
wordpress2markdown/utest_WordpressToMarkdown.py
wordpress2markdown.egg-info/PKG-INFO
wordpress2markdown.egg-info/SOURCES.txt
wordpress2markdown.egg-info/dependency_links.txt
wordpress2markdown.egg-info/top_level.txt