Metadata-Version: 1.1
Name: wordpress2markdown
Version: 0.40
Summary: A script to convert wordpress.com html into markdown.
Home-page: https://bitbucket.org/davidcorne/wordpress-to-markdown
Author: David Corne
Author-email: davidcorne@gmail.com
License: GPLv3
Keywords: wordpress html markdown convert utility
Platform: UNKNOWN
Classifier: Intended Audience :: Developers
Classifier: License :: OSI Approved :: GNU General Public License v3 or later (GPLv3+)
Classifier: Natural Language :: English
Classifier: Operating System :: OS Independent
Classifier: Programming Language :: Python
